<?xml version="1.0" encoding="UTF-8"?>
<binding:binding id="homeconnect"
        xmlns:xsi="http://www.w3.org/2001/XMLSchema-instance"
        xmlns:binding="http://eclipse.org/smarthome/schemas/binding/v1.0.0"
        xsi:schemaLocation="http://eclipse.org/smarthome/schemas/binding/v1.0.0 http://eclipse.org/smarthome/schemas/binding-1.0.0.xsd">

    <name>Homeconnect Binding</name>
    <description>This is the OpenHab binding for household devices with homeconnect service.</description>
    <author>Stefan Foydl</author>
    
    <service-id>org.openhab.homeconnect</service-id>
    

</binding:binding>